juujian/__init__.py
juujian/utility_functions.py
juujian-0.0.9.dist-info/LICENSE
juujian-0.0.9.dist-info/METADATA
juujian-0.0.9.dist-info/WHEEL
juujian-0.0.9.dist-info/top_level.txt
juujian-0.0.9.dist-info/RECORD
