Metadata-Version: 2.1
Name: juujian
Version: 0.0.9
Summary: Various web scraping and data science related tools. 
Home-page: UNKNOWN
Author: Julian Barg
Author-email: barg.julian@gmail.com
License: UNKNOWN
Platform: UNKNOWN
